Metadata-Version: 1.0
Name: jdlfactory
Version: 0.4
Summary: Description text
Home-page: https://github.com/tklijnsma/jdlfactory.git
Author: Thomas Klijnsma
Author-email: tklijnsm@gmail.com
License: BSD 3-Clause License
Platform: UNKNOWN
